<annotation>
	<folder>train</folder>
	<filename>240.jpg</filename>
	<path>C:\Users\rishi\virtual env test\pothole\models\research\object_detection\images\train\240.jpg</path>
	<source>
		<database>Unknown</database>
	</source>
	<size>
		<width>1500</width>
		<height>1101</height>
		<depth>3</depth>
	</size>
	<segmented>0</segmented>
	<object>
		<name>pothole</name>
		<pose>Unspecified</pose>
		<truncated>0</truncated>
		<difficult>0</difficult>
		<bndbox>
			<xmin>61</xmin>
			<ymin>415</ymin>
			<xmax>561</xmax>
			<ymax>641</ymax>
		</bndbox>
	</object>
	<object>
		<name>pothole</name>
		<pose>Unspecified</pose>
		<truncated>0</truncated>
		<difficult>0</difficult>
		<bndbox>
			<xmin>822</xmin>
			<ymin>374</ymin>
			<xmax>1088</xmax>
			<ymax>449</ymax>
		</bndbox>
	</object>
	<object>
		<name>pothole</name>
		<pose>Unspecified</pose>
		<truncated>1</truncated>
		<difficult>0</difficult>
		<bndbox>
			<xmin>1020</xmin>
			<ymin>435</ymin>
			<xmax>1500</xmax>
			<ymax>532</ymax>
		</bndbox>
	</object>
	<object>
		<name>pothole</name>
		<pose>Unspecified</pose>
		<truncated>0</truncated>
		<difficult>0</difficult>
		<bndbox>
			<xmin>832</xmin>
			<ymin>169</ymin>
			<xmax>1390</xmax>
			<ymax>320</ymax>
		</bndbox>
	</object>
	<object>
		<name>pothole</name>
		<pose>Unspecified</pose>
		<truncated>0</truncated>
		<difficult>0</difficult>
		<bndbox>
			<xmin>24</xmin>
			<ymin>232</ymin>
			<xmax>1284</xmax>
			<ymax>1003</ymax>
		</bndbox>
	</object>
</annotation>
